openbb_futures/__init__.py
openbb_futures/futures_router.py
openbb_futures/py.typed
openbb_futures-1.0.0b0.dist-info/METADATA
openbb_futures-1.0.0b0.dist-info/WHEEL
openbb_futures-1.0.0b0.dist-info/entry_points.txt
openbb_futures-1.0.0b0.dist-info/RECORD
