Metadata-Version: 2.1
Name: openbb-futures
Version: 1.0.0b0
Summary: Futures extension for OpenBB
Author: OpenBB Team
Author-email: hello@openbb.co
Requires-Python: >=3.8,<4.0
Classifier: Programming Language :: Python :: 3
Classifier: Programming Language :: Python :: 3.8
Classifier: Programming Language :: Python :: 3.9
Classifier: Programming Language :: Python :: 3.10
Classifier: Programming Language :: Python :: 3.11
Classifier: Programming Language :: Python :: 3.12
Requires-Dist: openbb-core (>=1.0.0b0,<2.0.0)
